dated_translator/Lookup.py
dated_translator/__init__.py
dated_translator/exceptions.py
dated_translator-0.1.1.dist-info/WHEEL
dated_translator-0.1.1.dist-info/METADATA
dated_translator-0.1.1.dist-info/RECORD
