Metadata-Version: 2.1
Name: dated-translator
Version: 0.1.1
Summary: A Python package that helps translate from one term to another, depending on a passed date, from a CSV that contains some verified information.
Home-page: https://github.com/Living-with-machines/dated-translator
Author: Kalle Westerling
Author-email: kalle.westerling@bl.uk
Requires-Python: >=3.9,<4.0
Classifier: Programming Language :: Python :: 3
Classifier: Programming Language :: Python :: 3.10
Classifier: Programming Language :: Python :: 3.9
Requires-Dist: pandas (>=1.4.1,<2.0.0)
Project-URL: Repository, https://github.com/Living-with-machines/dated-translator
